{
  "dim": {
    "DEFAULT": "#70666E",
    "50": "#F0EFF0",
    "100": "#E2DFE1",
    "200": "#C7C2C6",
    "300": "#AAA2A8",
    "400": "#8F848D",
    "500": "#70666E",
    "600": "#5B5359",
    "700": "#433D42",
    "800": "#2D292D",
    "900": "#151315",
    "950": "#0B0A0A"
  },
  "mauve": {
    "DEFAULT": "#957099",
    "50": "#F0EAF0",
    "100": "#E8DEE7",
    "200": "#D5C3D5",
    "300": "#BEA6BF",
    "400": "#AA8BAC",
    "500": "#957099",
    "600": "#7B597D",
    "700": "#5E445F",
    "800": "#412F41",
    "900": "#241923",
    "950": "#150F14"
  },
  "plum": {
    "DEFAULT": "#512438",
    "50": "#F1DFE7",
    "100": "#E6C6D5",
    "200": "#CE92AD",
    "300": "#B55983",
    "400": "#853056",
    "500": "#512438",
    "600": "#431E2F",
    "700": "#351825",
    "800": "#27111B",
    "900": "#190B11",
    "950": "#12080C"
  },
  "olivine": {
    "DEFAULT": "#88B177",
    "50": "#ECF4ED",
    "100": "#DFECDF",
    "200": "#C6DEC5",
    "300": "#B0CFAB",
    "400": "#9BC091",
    "500": "#88B177",
    "600": "#659857",
    "700": "#4A7543",
    "800": "#325430",
    "900": "#1C311D",
    "950": "#111D12"
  }
}
